.gitignore
.hgignore
.travis.yml
CHANGES.rst
CONTRIBUTORS.rst
MANIFEST.in
README.rst
TODO.txt
bootstrap.py
buildout.cfg
buildout3.cfg
setup.py
versions.cfg
collective/__init__.py
collective.recipe.solrinstance.egg-info/PKG-INFO
collective.recipe.solrinstance.egg-info/SOURCES.txt
collective.recipe.solrinstance.egg-info/dependency_links.txt
collective.recipe.solrinstance.egg-info/entry_points.txt
collective.recipe.solrinstance.egg-info/namespace_packages.txt
collective.recipe.solrinstance.egg-info/not-zip-safe
collective.recipe.solrinstance.egg-info/requires.txt
collective.recipe.solrinstance.egg-info/top_level.txt
collective/recipe/__init__.py
collective/recipe/solrinstance/README.txt
collective/recipe/solrinstance/__init__.py
collective/recipe/solrinstance/templates/jetty.xml.tmpl
collective/recipe/solrinstance/templates/log4j.properties.tmpl
collective/recipe/solrinstance/templates/logging.properties.tmpl
collective/recipe/solrinstance/templates/schema.xml.tmpl
collective/recipe/solrinstance/templates/solr-instance.tmpl
collective/recipe/solrinstance/templates/solr.xml.tmpl
collective/recipe/solrinstance/templates/solrconfig.xml.tmpl
collective/recipe/solrinstance/templates/stopwords.txt.tmpl
collective/recipe/solrinstance/templates4/jetty.xml.tmpl
collective/recipe/solrinstance/templates4/log4j.properties.tmpl
collective/recipe/solrinstance/templates4/logging.properties.tmpl
collective/recipe/solrinstance/templates4/schema.xml.tmpl
collective/recipe/solrinstance/templates4/solr-instance.tmpl
collective/recipe/solrinstance/templates4/solr.xml.tmpl
collective/recipe/solrinstance/templates4/solrconfig.xml.tmpl
collective/recipe/solrinstance/templates4/stopwords.txt.tmpl
collective/recipe/solrinstance/tests/__init__.py
collective/recipe/solrinstance/tests/test_doctests.py
collective/recipe/solrinstance/tests/test_solr_4.py