Metadata-Version: 1.1
Name: collective.recipe.solrinstance
Version: 5.3.2
Summary: zc.buildout to configure a solr instance
Home-page: http://pypi.python.org/pypi/collective.recipe.solrinstance
Author: Kai Lautaportti
Author-email: kai.lautaportti@hexagonit.fi
License: ZPL
Platform: UNKNOWN
Classifier: Framework :: Buildout
Classifier: Intended Audience :: Developers
Classifier: License :: OSI Approved :: Zope Public License
Classifier: Topic :: Software Development :: Build Tools
